LICENSE
README.md
setup.py
v2x_sim_visualizer/__init__.py
v2x_sim_visualizer/utils.py
v2x_sim_visualizer.egg-info/PKG-INFO
v2x_sim_visualizer.egg-info/SOURCES.txt
v2x_sim_visualizer.egg-info/dependency_links.txt
v2x_sim_visualizer.egg-info/requires.txt
v2x_sim_visualizer.egg-info/top_level.txt